ai_chatter/__about__.py
ai_chatter/__init__.py
ai_chatter/enums.py
ai_chatter/scripts.py
ai_chatter/apps/__init__.py
ai_chatter/apps/base.py
ai_chatter/apps/chat.py
ai_chatter/apps/howto.py
ai_chatter/apps/web.py
ai_chatter/communication/__init__.py
ai_chatter/communication/base.py
ai_chatter/communication/cli.py
ai_chatter/db/__init__.py
ai_chatter/db/base.py
ai_chatter/db/chat.py
ai_chatter/utils/__init__.py
ai_chatter/utils/config.py
ai_chatter-0.0.1a1.dist-info/METADATA
ai_chatter-0.0.1a1.dist-info/WHEEL
ai_chatter-0.0.1a1.dist-info/entry_points.txt
ai_chatter-0.0.1a1.dist-info/licenses/LICENSE.txt
ai_chatter-0.0.1a1.dist-info/RECORD
