Metadata-Version: 2.1
Name: ai-chatter
Version: 0.0.1a1
Project-URL: Documentation, https://github.com/FynnFreyer/ai-chatter#readme
Project-URL: Issues, https://github.com/FynnFreyer/ai-chatter/issues
Project-URL: Source, https://github.com/FynnFreyer/ai-chatter
Author-email: Fynn Freyer <fynn.freyer@googlemail.com>
License-Expression: AGPL-3.0-or-later
License-File: LICENSE.txt
Keywords: ai,chatbot,chatgpt
Classifier: Development Status :: 2 - Pre-Alpha
Classifier: License :: OSI Approved :: GNU Affero General Public License v3 or later (AGPLv3+)
Classifier: Programming Language :: Python
Classifier: Programming Language :: Python :: 3 :: Only
Classifier: Programming Language :: Python :: 3.8
Classifier: Programming Language :: Python :: 3.9
Classifier: Programming Language :: Python :: 3.10
Classifier: Programming Language :: Python :: 3.11
Classifier: Programming Language :: Python :: Implementation :: CPython
Classifier: Programming Language :: Python :: Implementation :: PyPy
Requires-Python: >=3.8
Requires-Dist: openai
Requires-Dist: platformdirs
Requires-Dist: pydantic-settings
Requires-Dist: sqlalchemy
Provides-Extra: dev
Requires-Dist: hatch; extra == 'dev'
Requires-Dist: pip-tools; extra == 'dev'
Requires-Dist: twine; extra == 'dev'
Provides-Extra: web
Requires-Dist: bs4; extra == 'web'
Requires-Dist: markdownify; extra == 'web'
Requires-Dist: requests-html; extra == 'web'
